srt2soundfx/__init__.py
srt2soundfx/audio_placer.py
srt2soundfx/chatgpt_interface.py
srt2soundfx/core.py
srt2soundfx/sound_generator.py
srt2soundfx/srt_merger.py
srt2soundfx/srt_parser.py
srt2soundfx-1.0.2.dist-info/LICENSE
srt2soundfx-1.0.2.dist-info/METADATA
srt2soundfx-1.0.2.dist-info/WHEEL
srt2soundfx-1.0.2.dist-info/top_level.txt
srt2soundfx-1.0.2.dist-info/RECORD
