Metadata-Version: 2.1
Name: srt2soundfx
Version: 1.0.2
Summary: An audiobook sound effect generator that transforms SRT files into immersive audio experiences. It parses SRT files, uses ChatGPT to create sound effect prompts, generates sounds via the ElevenLabs API, and syncs the audio on an MP3 timeline.
Home-page: https://github.com/stefaner1/SRT2SoundFX
Classifier: Programming Language :: Python :: 3
Classifier: License :: OSI Approved :: MIT License
Classifier: Operating System :: OS Independent
Requires-Python: >=3.7
License-File: LICENSE
Requires-Dist: openai==1.42.0
Requires-Dist: python-dotenv
Requires-Dist: elevenlabs==1.7.0
